weightedset/__init__.py
weightedset/_weighted_set.py
weightedset-1.0.0.dist-info/LICENSE
weightedset-1.0.0.dist-info/WHEEL
weightedset-1.0.0.dist-info/METADATA
weightedset-1.0.0.dist-info/RECORD
