Metadata-Version: 2.1
Name: weightedset
Version: 1.0.0
Summary: Weighted set
Home-page: https://github.com/Oovvuu/weightedset
License: MIT
Keywords: weighted-set
Author: Gary Donovan
Author-email: gazza@gazza.id.au
Requires-Python: >=3.7,<4.0
Classifier: Development Status :: 5 - Production/Stable
Classifier: Intended Audience :: Developers
Classifier: License :: OSI Approved :: MIT License
Classifier: Natural Language :: English
Classifier: Operating System :: OS Independent
Classifier: Programming Language :: Python
Classifier: Programming Language :: Python :: 3
Classifier: Programming Language :: Python :: 3 :: Only
Classifier: Programming Language :: Python :: 3.7
Classifier: Programming Language :: Python :: 3.8
Classifier: Topic :: Software Development :: Libraries
Project-URL: Documentation, https://github.com/Oovvuu/weightedset
Project-URL: Repository, https://github.com/Oovvuu/weightedset
